fastpivot/test_sparse.py
fastpivot/pivot_sparse.py
fastpivot/__init__.py
fastpivot/example.py
fastpivot/pivot.cpython-37m-x86_64-linux-gnu.so
fastpivot/benchmarks.py
fastpivot/test_pivot.py
fastpivot-0.1.13.dist-info/LICENSE
fastpivot-0.1.13.dist-info/METADATA
fastpivot-0.1.13.dist-info/WHEEL
fastpivot-0.1.13.dist-info/top_level.txt
fastpivot-0.1.13.dist-info/RECORD
