Metadata-Version: 2.1
Name: fastpivot
Version: 0.1.13
Summary: Fast implementation of pandas.pivot_table
Home-page: https://github.com/SethEBaldwin/fastpivot
Author: Seth Baldwin
Author-email: seth.e.baldwin@gmail.com
Project-URL: Bug Tracker, https://github.com/SethEBaldwin/fastpivot/issues
Classifier: Programming Language :: Python :: 3
Classifier: License :: OSI Approved :: MIT License
Classifier: Operating System :: OS Independent
Requires-Python: >=3.7
License-File: LICENSE
Requires-Dist: numpy >=1.19.0
Requires-Dist: pandas >=1.0.0
Requires-Dist: scipy >=1.6.0
